setup.py
ventura/__init__.py
ventura/_hpath.py
ventura/_hweb.py
ventura/_hxml.py
ventura/_hzip.py
ventura/ventura.py
ventura.egg-info/PKG-INFO
ventura.egg-info/SOURCES.txt
ventura.egg-info/dependency_links.txt
ventura.egg-info/top_level.txt